CHANGELOG.txt
MANIFEST.in
README.rst
ez_setup.py
setup.py
sparsesvd.pxd
sparsesvd.pyx
test.py
Pyrex/__init__.py
Pyrex/__init__.pyc
Pyrex/Distutils/__init__.py
Pyrex/Distutils/__init__.pyc
Pyrex/Distutils/build_ext.py
Pyrex/Distutils/build_ext.pyc
SVDLIBC/Makefile
SVDLIBC/las2.c
SVDLIBC/svdlib.c
SVDLIBC/svdlib.h
SVDLIBC/svdutil.c
SVDLIBC/svdutil.h
SVDLIBC/Manual/SVD_F_DB.html
SVDLIBC/Manual/SVD_F_DT.html
SVDLIBC/Manual/SVD_F_SB.html
SVDLIBC/Manual/SVD_F_ST.html
SVDLIBC/Manual/SVD_F_STH.html
SVDLIBC/Manual/index.html
SVDLIBC/Manual/svdlib.h
sparsesvd.egg-info/PKG-INFO
sparsesvd.egg-info/SOURCES.txt
sparsesvd.egg-info/dependency_links.txt
sparsesvd.egg-info/not-zip-safe
sparsesvd.egg-info/requires.txt
sparsesvd.egg-info/top_level.txt