Metadata-Version: 1.0
Name: sparsesvd
Version: 0.2.0
Summary: Python module that wraps SVDLIBC, a library for sparse Singular Value Decomposition.
Home-page: http://pypi.python.org/pypi/sparsesvd
Author: Radim Rehurek
Author-email: radimrehurek@seznam.cz
License: BSD
Download-URL: http://pypi.python.org/pypi/sparsesvd
Keywords: Singular Value Decomposition,SVD,sparse SVD
Platform: any
Classifier: Development Status :: 4 - Beta
Classifier: Environment :: Console
Classifier: Intended Audience :: Science/Research
Classifier: Operating System :: OS Independent
Classifier: Programming Language :: Python :: 2.5
Classifier: Programming Language :: Python :: 2.6
Classifier: Programming Language :: Python :: 2.7
Classifier: Programming Language :: Python :: 3.2
Classifier: Topic :: Scientific/Engineering :: Mathematics
Classifier: Topic :: Scientific/Engineering :: Artificial Intelligence
Classifier: Topic :: Scientific/Engineering :: Information Analysis
Classifier: Topic :: Text Processing :: Linguistic
Classifier: License :: OSI Approved :: BSD License
